pejecoins/__init__.py
pejecoins/example.py
pejecoins/tempCodeRunnerFile.py
pejecoins-1.0.0.dist-info/METADATA
pejecoins-1.0.0.dist-info/WHEEL
pejecoins-1.0.0.dist-info/RECORD
